README.md
setup.py
alibabacloud_openapi_util/__init__.py
alibabacloud_openapi_util/client.py
alibabacloud_openapi_util/sm3.py
alibabacloud_openapi_util.egg-info/PKG-INFO
alibabacloud_openapi_util.egg-info/SOURCES.txt
alibabacloud_openapi_util.egg-info/dependency_links.txt
alibabacloud_openapi_util.egg-info/requires.txt
alibabacloud_openapi_util.egg-info/top_level.txt