Metadata-Version: 1.1
Name: alibabacloud-openapi-util
Version: 0.1.5
Summary: Aliyun Tea OpenApi Library for Python
Home-page: https://github.com/aliyun/darabonba-openapi-util
Author: Alibaba Cloud
Author-email: alibaba-cloud-sdk-dev-team@list.alibaba-inc.com
License: Apache License 2.0
Keywords: alibabacloud_openapi_util
Platform: any
Classifier: Development Status :: 4 - Beta
Classifier: Intended Audience :: Developers
Classifier: License :: OSI Approved :: Apache Software License
Classifier: Programming Language :: Python
Classifier: Programming Language :: Python :: 3
Classifier: Programming Language :: Python :: 3.6
Classifier: Programming Language :: Python :: 3.7
Classifier: Programming Language :: Python :: 3.8
Classifier: Topic :: Software Development
